Workbook

Sheet Sales_Data
A1: ORDER ID | B1: DATE | C1: PRODUCT | D1: CATEGORY | E1: REGION | F1: SALESPERSON | G1: QUANTITY | H1: SALES | I1: COST | J1: PROFIT
A2: ORD001 | B2: 46023 | C2: Laptop | D2: Electronics | E2: Bhopal | F2: Rahul | G2: 2 | H2: 90000 | I2: 75000 | J2: =H2-I2 -> 15000
A3: ORD002 | B3: 46025 | C3: Mouse | D3: Accessories | E3: Indore | F3: Amit | G3: 10 | H3: 8000 | I3: 5500 | J3: =H3-I3 -> 2500
A4: ORD003 | B4: 46027 | C4: Mobile | D4: Electronics | E4: Bhopal | F4: Neha | G4: 5 | H4: 75000 | I4: 62000 | J4: =H4-I4 -> 13000
A5: ORD004 | B5: 46030 | C5: Keyboard | D5: Accessories | E5: Nagpur | F5: Rahul | G5: 8 | H5: 12000 | I5: 8000 | J5: =H5-I5 -> 4000
A6: ORD005 | B6: 46034 | C6: Monitor | D6: Electronics | E6: Indore | F6: Priya | G6: 3 | H6: 45000 | I6: 35000 | J6: =H6-I6 -> 10000
A7: ORD006 | B7: 46037 | C7: Printer | D7: Electronics | E7: Bhopal | F7: Amit | G7: 2 | H7: 30000 | I7: 24000 | J7: =H7-I7 -> 6000
A8: ORD007 | B8: 46042 | C8: Laptop | D8: Electronics | E8: Nagpur | F8: Neha | G8: 1 | H8: 45000 | I8: 37500 | J8: =H8-I8 -> 7500
A9: ORD008 | B9: 46047 | C9: Mouse | D9: Accessories | E9: Indore | F9: Priya | G9: 15 | H9: 12000 | I9: 8250 | J9: =H9-I9 -> 3750
A10: ORD009 | B10: 46055 | C10: Mobile | D10: Electronics | E10: Bhopal | F10: Rahul | G10: 4 | H10: 60000 | I10: 50000 | J10: =H10-I10 -> 10000
A11: ORD010 | B11: 46058 | C11: Keyboard | D11: Accessories | E11: Nagpur | F11: Amit | G11: 4 | H11: 60000 | I11: 46000 | J11: =H11-I11 -> 14000
A12: ORD011 | B12: 46063 | C12: Monitor | D12: Electronics | E12: Bhopal | F12: Neha | G12: 12 | H12: 18000 | I12: 12000 | J12: =H12-I12 -> 6000
A13: ORD012 | B13: 46067 | C13: Printer | D13: Electronics | E13: Indore | F13: Priya | G13: 3 | H13: 45000 | I13: 36000 | J13: =H13-I13 -> 9000
... A22: ORD021 | B22: 46111 | C22: Keyboard | D22: Accessories | E22: Nagpur | F22: Amit | G22: 20 | H22: 120000 | I22: 85200 | J22: =H22-I22 -> 34800

Sheet Calculations
A1: KPI | B1: Formula | D1: Month | E1: Sales | G1: Category | H1: Sales | J1: Region | K1: Sales | M1: Salesperson | N1: Sales
A2: Total Sales | B2: =SUM(Sales_Data!H:H) -> 1153500 | D2: January | E2: =SUMPRODUCT((MONTH(Sales_Data!$B$2:$B$21)=MONTH(DATEVALUE(D2&" 1")))*Sales_Data!$H$2:$H$21) -> 317000 | G2: Electronics | H2: =SUMIF(Sales_Data!$D:$D,G2,Sales_Data!$H:$H) -> 903000 | J2: Bhopal | K2: =SUMIF(Sales_Data!$E:$E,J2,Sales_Data!$H:$H) -> 528000 | M2: Rahul | N2: =SUMIF(Sales_Data!$F:$F,M2,Sales_Data!$H:$H) -> 319500
A3: Total Cost | B3: =SUM(Sales_Data!I:I) -> 915950 | D3: February | E3: =SUMPRODUCT((MONTH(Sales_Data!$B$2:$B$21)=MONTH(DATEVALUE(D3&" 1")))*Sales_Data!$H$2:$H$21) -> 334000 | G3: Accessories | H3: =SUMIF(Sales_Data!$D:$D,G3,Sales_Data!$H:$H) -> 250500 | J3: indore | K3: =SUMIF(Sales_Data!$E:$E,J3,Sales_Data!$H:$H) -> 312500 | M3: Amit | N3: =SUMIF(Sales_Data!$F:$F,M3,Sales_Data!$H:$H) -> 0
A4: Total Profit | B4: =SUM(Sales_Data!J:J) -> 237550 | D4: March | E4: =SUMPRODUCT((MONTH(Sales_Data!$B$2:$B$21)=MONTH(DATEVALUE(D4&" 1")))*Sales_Data!$H$2:$H$21) -> 382500 | J4: nagpur | K4: =SUMIF(Sales_Data!$E:$E,J4,Sales_Data!$H:$H) -> 313000 | M4: Priya | N4: =SUMIF(Sales_Data!$F:$F,M4,Sales_Data!$H:$H) -> 222000
A5: Total Quantity | B5: =SUM(Sales_Data!G:G) -> 147 | M5: Neha | N5: =SUMIF(Sales_Data!$F:$F,M5,Sales_Data!$H:$H) -> 318000
A6: Total Order | B6: =COUNTA(Sales_Data!A:A)-1 -> 21
A7: Profit Margin | B7: =B4/B2 -> 0.20593845

Sheet Sales_Dashboard
A1: SALES PERFORMANCE DASHBOARD
A3: Total Sales | C3: Total Cost | E3: Total Profit | G3: Total Quantity | I3: Total Orders
A4: =Calculations!B2 -> 1153500 | C4: =Calculations!B3 -> 915950 | E4: =Calculations!B4 -> 237550 | G4: =Calculations!B5 -> 147 | I4: =Calculations!B6 -> 21
